wronai/README.md
wronai/__init__.py
wronai/__main__.py
wronai/cli.py
wronai/cli_new.py
wronai/create_custom_model.py
wronai/models/base.py
wronai/models/huggingface.py
wronai/models/ollama.py
wronai/pyproject.toml
wronai/test_converted_model.py
wronai/tests/__init__.py
wronai/tests/test_cli.py
wronai/utils/__init__.py
wronai-0.1.5.dist-info/LICENSE
wronai-0.1.5.dist-info/METADATA
wronai-0.1.5.dist-info/WHEEL
wronai-0.1.5.dist-info/entry_points.txt
wronai-0.1.5.dist-info/RECORD
