Metadata-Version: 2.3
Name: wronai
Version: 0.1.5
Summary: End-to-end LLM model building, fine-tuning, and deployment toolkit
License: Apache-2.0
Keywords: llm,ai,machine-learning,huggingface,ollama,fine-tuning
Author: WronAI Team
Author-email: info@softreck.dev
Requires-Python: >=3.8,<4.0
Classifier: Development Status :: 3 - Alpha
Classifier: Intended Audience :: Developers
Classifier: Intended Audience :: Science/Research
Classifier: License :: OSI Approved :: Apache Software License
Classifier: Programming Language :: Python :: 3
Classifier: Programming Language :: Python :: 3.8
Classifier: Programming Language :: Python :: 3.9
Classifier: Programming Language :: Python :: 3.10
Classifier: Programming Language :: Python :: 3.11
Classifier: Programming Language :: Python :: 3.12
Classifier: Programming Language :: Python :: 3.13
Classifier: Topic :: Scientific/Engineering
Classifier: Topic :: Scientific/Engineering :: Artificial Intelligence
Classifier: Topic :: Software Development
Classifier: Topic :: Software Development :: Libraries
Classifier: Topic :: Software Development :: Libraries :: Python Modules
Requires-Dist: accelerate (>=0.25.0,<0.26.0)
Requires-Dist: bitsandbytes (>=0.41.0,<0.42.0)
Requires-Dist: click (>=8.1.7,<9.0.0)
Requires-Dist: huggingface-hub (>=0.19.4,<0.20.0)
Requires-Dist: jinja2 (>=3.1.2,<4.0.0)
Requires-Dist: loguru (>=0.7.2,<0.8.0)
Requires-Dist: peft (>=0.7.0,<0.8.0)
Requires-Dist: pydantic (>=2.4.2,<3.0.0)
Requires-Dist: python-dotenv (>=1.0.0,<2.0.0)
Requires-Dist: pyyaml (>=6.0.1,<7.0.0)
Requires-Dist: requests (>=2.31.0,<3.0.0)
Requires-Dist: rich (>=13.7.0,<14.0.0)
Requires-Dist: torch (>=2.0.0,<3.0.0)
Requires-Dist: transformers (>=4.35.0,<5.0.0)
Project-URL: Bug Tracker, https://github.com/wronai/llm-demo/issues
Project-URL: Documentation, https://github.com/wronai/llm-demo#readme
Project-URL: Homepage, https://github.com/wronai/llm-demo
Project-URL: Repository, https://github.com/wronai/llm-demo
Project-URL: Source Code, https://github.com/wronai/llm-demo
